Workbook

Sheet UAT
C1: https://www.jnjmedtech.com/
A2: From | B2: To | C2: New Destination | D2: Anchor Text | E2: Alt Text | F2: Status Code | G2: Status | H2: Path Type | I2: Link Path | J2: Link Position | K2: Link Origin
A3: https://jnj-uat.lower.jnj.brightspot.cloud/latest-news | B3: https://thenext.jnjmedtech.com/medtech-insights/post/what-roles-do-pfa-and-rfa-play-in-the-treatment-of-afib | C3: =IFERROR(XLOOKUP(B3,'Deduped URLs'!A:A,'Deduped URLs'!B:B,""),"") | E3: Surgeon using AI in surgery for advanced medical procedures | F3: 301 | G3: Moved Permanently | H3: Absolute | I3: //body/div[@id='main']/main/bsp-listcarousel/div[@class='PageList-items-wrap']/div[1]/div/div/div[5]/bsp-pagepromo/div[@class='PagePromo-media']/a | J3: Content | K3: HTML & Rendered HTML
A4: https://jnj-uat.lower.jnj.brightspot.cloud/latest-news | B4: https://thenext.jnjmedtech.com/medtech-insights/post/what-roles-do-pfa-and-rfa-play-in-the-treatment-of-afib | C4: =IFERROR(XLOOKUP(B4,'Deduped URLs'!A:A,'Deduped URLs'!B:B,""),"") | D4: An electrophysiologist discusses the role of cardiac ablation in the treatment of AFib | F4: 301 | G4: Moved Permanently | H4: Absolute | I4: //body/div[@id='main']/main/bsp-listcarousel/div[@class='PageList-items-wrap']/div[1]/div/div/div[5]/bsp-pagepromo/div[@class='PagePromo-content']/h3/a | J4: Content | K4: HTML & Rendered HTML
A5: https://jnj-uat.lower.jnj.brightspot.cloud/latest-news | B5: https://thenext.jnjmedtech.com/medtech-insights/post/what-roles-do-pfa-and-rfa-play-in-the-treatment-of-afib | C5: =IFERROR(XLOOKUP(B5,'Deduped URLs'!A:A,'Deduped URLs'!B:B,""),"") | D5: Read more | F5: 301 | G5: Moved Permanently | H5: Absolute | I5: //body/div[@id='main']/main/bsp-listcarousel/div[@class='PageList-items-wrap']/div[1]/div/div/div[5]/bsp-pagepromo/div[@class='PagePromo-content']/div[@class='PagePromo-ctaLink']/a | J5: Content | K5: HTML & Rendered HTML
A6: https://jnj-uat.lower.jnj.brightspot.cloud/latest-news | B6: https://thenext.jnjmedtech.com/medtech-insights/post/firing-up-the-next-step-in-surgical-stapling | C6: =IFERROR(XLOOKUP(B6,'Deduped URLs'!A:A,'Deduped URLs'!B:B,""),"") | D6: Firing up the next step in surgical stapling | F6: 301 | G6: Moved Permanently | H6: Absolute | I6: //body/div[@id='main']/main/bsp-pagepromo[@id='the-future-of-knee-replacement-surgery']/div/div[@class='PagePromoModuleC-CallOutA-contentWrap']/div/h3/a | J6: Content | K6: HTML & Rendered HTML
A7: https://jnj-uat.lower.jnj.brightspot.cloud/latest-news | B7: https://thenext.jnjmedtech.com/medtech-insights/post/firing-up-the-next-step-in-surgical-stapling | C7: =IFERROR(XLOOKUP(B7,'Deduped URLs'!A:A,'Deduped URLs'!B:B,""),"") | D7: Learn more | F7: 301 | G7: Moved Permanently | H7: Absolute | I7: //body/div[@id='main']/main/bsp-pagepromo[@id='the-future-of-knee-replacement-surgery']/div/div[@class='PagePromoModuleC-CallOutA-contentWrap']/div/div/a | J7: Content | K7: HTML & Rendered HTML
A8: https://jnj-uat.lower.jnj.brightspot.cloud/latest-news | B8: https://thenext.jnjmedtech.com/medtech-insights/post/firing-up-the-next-step-in-surgical-stapling | C8: =IFERROR(XLOOKUP(B8,'Deduped URLs'!A:A,'Deduped URLs'!B:B,""),"") | E8: A surgeon using a surgical stapler | F8: 301 | G8: Moved Permanently | H8: Absolute | I8: //body/div[@id='main']/main/bsp-pagepromo[@id='the-future-of-knee-replacement-surgery']/div/div[@class='PagePromo-media']/a | J8: Content | K8: HTML & Rendered HTML
A9: https://jnj-uat.lower.jnj.brightspot.cloud/future-of-surgery | B9: https://thenext.jnjmedtech.com/medtech-insights/post/firing-up-the-next-step-in-surgical-stapling | C9: =IFERROR(XLOOKUP(B9,'Deduped URLs'!A:A,'Deduped URLs'!B:B,""),"") | E9: Future of Surgery Landing Page Alt.png | F9: 301 | G9: Moved Permanently | H9: Absolute | I9: //body/div[@id='main']/main/bsp-list-loadmore[@id='list-module-900000']/div/div[2]/bsp-pagepromo/div[@class='PagePromo-media']/a | J9: Content | K9: HTML & Rendered HTML
A10: https://jnj-uat.lower.jnj.brightspot.cloud/future-of-surgery | B10: https://thenext.jnjmedtech.com/medtech-insights/post/firing-up-the-next-step-in-surgical-stapling | C10: =IFERROR(XLOOKUP(B10,'Deduped URLs'!A:A,'Deduped URLs'!B:B,""),"") | D10: Firing up the next step in surgical stapling | F10: 301 | G10: Moved Permanently | H10: Absolute | I10: //body/div[@id='main']/main/bsp-list-loadmore[@id='list-module-900000']/div/div[2]/bsp-pagepromo/div[@class='PagePromo-content']/h2/a | J10: Content | K10: HTML & Rendered HTML
A11: https://jnj-uat.lower.jnj.brightspot.cloud/future-of-surgery | B11: https://thenext.jnjmedtech.com/medtech-insights/post/firing-up-the-next-step-in-surgical-stapling | C11: =IFERROR(XLOOKUP(B11,'Deduped URLs'!A:A,'Deduped URLs'!B:B,""),"") | D11: Read more | F11: 301 | G11: Moved Permanently | H11: Absolute | I11: //body/div[@id='main']/main/bsp-list-loadmore[@id='list-module-900000']/div/div[2]/bsp-pagepromo/div[@class='PagePromo-content']/div[@class='PagePromo-ctaLink']/a | J11: Content | K11: HTML & Rendered HTML
A12: https://jnj-uat.lower.jnj.brightspot.cloud/CH/latest-news/relier-industrie-et-universite-faconner-la-prochaine-generation-dinnovateurs-en-sante | B12: https://thenext.jnjmedtech.com/ | C12: https://www.jnjmedtech.com/ | D12: J&J MedTech | F12: 301 | G12: Moved Permanently | H12: Absolute | I12: //body/bsp-header/div[@class='Page-header-topNav-container']/nav/ul/li[1]/ul/li[@class='GlobalSiteNavigation-items-item'][3]/div/div/a | J12: Navigation | K12: HTML & Rendered HTML
A13: https://jnj-uat.lower.jnj.brightspot.cloud/CH/latest-news/relier-industrie-et-universite-faconner-la-prochaine-generation-dinnovateurs-en-sante | B13: https://thenext.jnjmedtech.com/ | C13: https://www.jnjmedtech.com/ | D13: J&J MedTech | F13: 301 | G13: Moved Permanently | H13: Absolute | I13: //body/bsp-header/div[@class='Page-header-topNav-container']/nav/ul/li[1]/div/ul/li[@class='GlobalSiteNavigation-items-item'][3]/div/div/a | J13: Navigation | K13: HTML & Rendered HTML
A14: https://jnj-uat.lower.jnj.brightspot.cloud/CH/de/nics-story | B14: https://thenext.jnjmedtech.com/ | C14: https://www.jnjmedtech.com/ | D14: J&J MedTech | F14: 301 | G14: Moved Permanently | H14: Absolute | I14: //body/bsp-header/div[@class='Page-header-topNav-container']/nav/ul/li[1]/ul/li[@class='GlobalSiteNavigation-items-item'][3]/div/div/a | J14: Navigation | K14: HTML & Rendered HTML
A15: https://jnj-uat.lower.jnj.brightspot.cloud/CH/de/nics-story | B15: https://thenext.jnjmedtech.com/ | C15: https://www.jnjmedtech.com/ | D15: J&J MedTech | F15: 301 | G15: Moved Permanently | H15: Absolute | I15: //body/bsp-header/div[@class='Page-header-topNav-container']/nav/ul/li[1]/div/ul/li[@class='GlobalSiteNavigation-items-item'][3]/div/div/a | J15: Navigation | K15: HTML & Rendered HTML
A16: https://jnj-uat.lower.jnj.brightspot.cloud/CH/de/zoes-story | B16: https://thenext.jnjmedtech.com/ | C16: https://www.jnjmedtech.com/ | D16: J&J MedTech | F16: 301 | G16: Moved Permanently | H16: Absolute | I16: //body/bsp-header/div[@class='Page-header-topNav-container']/nav/ul/li[1]/ul/li[@class='GlobalSiteNavigation-items-item'][3]/div/div/a | J16: Navigation | K16: HTML & Rendered HTML
A17: https://jnj-uat.lower.jnj.brightspot.cloud/CH/de/zoes-story | B17: https://thenext.jnjmedtech.com/ | C17: https://www.jnjmedtech.com/ | D17: J&J MedTech | F17: 301 | G17: Moved Permanently | H17: Absolute | I17: //body/bsp-header/div[@class='Page-header-topNav-container']/nav/ul/li[1]/div/ul/li[@class='GlobalSiteNavigation-items-item'][3]/div/div/a | J17: Navigation | K17: HTML & Rendered HTML
A18: https://jnj-uat.lower.jnj.brightspot.cloud/CH/de/data-privacy | B18: https://thenext.jnjmedtech.com/ | C18: https://www.jnjmedtech.com/ | D18: J&J MedTech | F18: 301 | G18: Moved Permanently | H18: Absolute | I18: //body/bsp-header/div[@class='Page-header-topNav-container']/nav/ul/li[1]/ul/li[@class='GlobalSiteNavigation-items-item'][3]/div/div/a | J18: Navigation | K18: HTML & Rendered HTML
A19: https://jnj-uat.lower.jnj.brightspot.cloud/CH/de/data-privacy | B19: https://thenext.jnjmedtech.com/ | C19: https://www.jnjmedtech.com/ | D19: J&J MedTech | F19: 301 | G19: Moved Permanently | H19: Absolute | I19: //body/bsp-header/div[@class='Page-header-topNav-container']/nav/ul/li[1]/div/ul/li[@class='GlobalSiteNavigation-items-item'][3]/div/div/a | J19: Navigation | K19: HTML & Rendered HTML
A20: https://jnj-uat.lower.jnj.brightspot.cloud/privacy-center/en-us/privacy-statement?s=00000195-202e-ddef-a3f7-213f11db0000&p=00000195-202a-ddef-a3f7-213b3e7b0000 | B20: https://thenext.jnjmedtech.com/ | C20: =IFERROR(XLOOKUP(B20,'Deduped URLs'!A:A,'Deduped URLs'!B:B,""),"") | D20: Medical devices & technology | F20: 301 | G20: Moved Permanently | H20: Absolute | I20: //body/bsp-header/div[@class='Page-header-topNav-container']/nav/ul/li[1]/ul/li[@class='GlobalSiteNavigation-items-item'][3]/div/div/a | J20: Navigation | K20: HTML & Rendered HTML
A21: https://jnj-uat.lower.jnj.brightspot.cloud/privacy-center/en-us/privacy-statement?s=00000195-202e-ddef-a3f7-213f11db0000&p=00000195-202a-ddef-a3f7-213b3e7b0000 | B21: https://thenext.jnjmedtech.com/ | C21: =IFERROR(XLOOKUP(B21,'Deduped URLs'!A:A,'Deduped URLs'!B:B,""),"") | D21: Medical devices & technology | F21: 301 | G21: Moved Permanently | H21: Absolute | I21: //body/bsp-header/div[@class='Page-header-topNav-container']/nav/ul/li[1]/div/ul/li[@class='GlobalSiteNavigation-items-item'][3]/div/div/a | J21: Navigation | K21: HTML & Rendered HTML
A22: https://jnj-uat.lower.jnj.brightspot.cloud/privacy-center/en-us/privacy-statement?s=00000195-202e-ddef-a3f7-213f11db0000&p=00000195-202a-ddef-a3f7-213b3e7b0000 | B22: https://thenext.jnjmedtech.com/ | C22: =IFERROR(XLOOKUP(B22,'Deduped URLs'!A:A,'Deduped URLs'!B:B,""),"") | D22: Medical devices & technology | F22: 301 | G22: Moved Permanently | H22: Absolute | I22: //body/footer/div/div[@class='Page-footer-columns']/div/div/bsp-footer-nav/ul/li[@class='FooterNavigation-items-item'][1]/div/ul/li[@class='FooterNavigationItem-items-item'][3]/a | J22: Navigation | K22: HTML & Rendered HTML
A23: https://jnj-uat.lower.jnj.brightspot.cloud/CH/fr | B23: https://thenext.jnjmedtech.com/ | C23: https://www.jnjmedtech.com/ | D23: J&J MedTech | F23: 301 | G23: Moved Permanently | H23: Absolute | I23: //body/bsp-header/div[@class='Page-header-topNav-container']/nav/ul/li[1]/ul/li[@class='GlobalSiteNavigation-items-item'][3]/div/div/a | J23: Navigation | K23: HTML & Rendered HTML
A24: https://jnj-uat.lower.jnj.brightspot.cloud/CH/fr | B24: https://thenext.jnjmedtech.com/ | C24: https://www.jnjmedtech.com/ | D24: J&J MedTech | F24: 301 | G24: Moved Permanently | H24: Absolute | I24: //body/bsp-header/div[@class='Page-header-topNav-container']/nav/ul/li[1]/div/ul/li[@class='GlobalSiteNavigation-items-item'][3]/div/div/a | J24: Navigation | K24: HTML & Rendered HTML
A25: https://jnj-uat.lower.jnj.brightspot.cloud/CH/de | B25: https://thenext.jnjmedtech.com/ | C25: https://www.jnjmedtech.com/ | D25: J&J MedTech | F25: 301 | G25: Moved Permanently | H25: Absolute | I25: //body/bsp-header/div[@class='Page-header-topNav-container']/nav/ul/li[1]/ul/li[@class='GlobalSiteNavigation-items-item'][3]/div/div/a | J25: Navigation | K25: HTML & Rendered HTML
A26: https://jnj-uat.lower.jnj.brightspot.cloud/CH/de | B26: https://thenext.jnjmedtech.com/ | C26: https://www.jnjmedtech.com/ | D26: J&J MedTech | F26: 301 | G26: Moved Permanently | H26: Absolute | I26: //body/bsp-header/div[@class='Page-header-topNav-container']/nav/ul/li[1]/div/ul/li[@class='GlobalSiteNavigation-items-item'][3]/div/div/a | J26: Navigation | K26: HTML & Rendered HTML
A27: https://jnj-uat.lower.jnj.brightspot.cloud/CH/ | B27: https://thenext.jnjmedtech.com/ | C27: https://www.jnjmedtech.com/ | D27: J&J MedTech | F27: 301 | G27: Moved Permanently | H27: Absolute | I27: //body/bsp-header/div[@class='Page-header-topNav-container']/nav/ul/li[1]/ul/li[@class='GlobalSiteNavigation-items-item'][3]/div/div/a | J27: Navigation | K27: HTML & Rendered HTML
A28: https://jnj-uat.lower.jnj.brightspot.cloud/CH/ | B28: https://thenext.jnjmedtech.com/ | C28: https://www.jnjmedtech.com/ | D28: J&J MedTech | F28: 301 | G28: Moved Permanently | H28: Absolute | I28: //body/bsp-header/div[@class='Page-header-topNav-container']/nav/ul/li[1]/div/ul/li[@class='GlobalSiteNavigation-items-item'][3]/div/div/a | J28: Navigation | K28: HTML & Rendered HTML
A29: https://jnj-uat.lower.jnj.brightspot.cloud/innovativemedicine/argentina/ | B29: https://thenext.jnjmedtech.com/ | C29: https://www.jnjmedtech.com/ | D29: Medical devices & technology | F29: 301 | G29: Moved Permanently | H29: Absolute | I29: //body/bsp-header/div[@class='Page-header-topNav-container']/nav/ul/li[1]/ul/li[@class='GlobalSiteNavigation-items-item'][3]/div/div/a | J29: Navigation | K29: HTML & Rendered HTML
A30: https://jnj-uat.lower.jnj.brightspot.cloud/innovativemedicine/argentina/ | B30: https://thenext.jnjmedtech.com/ | C30: https://www.jnjmedtech.com/ | D30: Medical devices & technology | F30: 301 | G30: Moved Permanently | H30: Absolute | I30: //body/bsp-header/div[@class='Page-header-topNav-container']/nav/ul/li[1]/div/ul/li[@class='GlobalSiteNavigation-items-item'][3]/div/div/a | J30: Navigation | K30: HTML & Rendered HTML
A31: https://jnj-uat.lower.jnj.brightspot.cloud/innovativemedicine/apac/ | B31: https://thenext.jnjmedtech.com/ | C31: https://www.jnjmedtech.com/ | D31: Medical devices & technology | F31: 301 | G31: Moved Permanently | H31: Absolute | I31: //body/bsp-header/div[@class='Page-header-topNav-container']/nav/ul/li[1]/ul/li[@class='GlobalSiteNavigation-items-item'][3]/div/div/a | J31: Navigation | K31: HTML & Rendered HTML
A32: https://jnj-uat.lower.jnj.brightspot.cloud/innovativemedicine/apac/ | B32: https://thenext.jnjmedtech.com/ | C32: https://www.jnjmedtech.com/ | D32: Medical devices & technology | F32: 301 | G32: Moved Permanently | H32: Absolute | I32: //body/bsp-header/div[@class='Page-header-topNav-container']/nav/ul/li[1]/div/ul/li[@class='GlobalSiteNavigation-items-item'][3]/div/div/a | J32: Navigation | K32: HTML & Rendered HTML
A33: https://jnj-uat.lower.jnj.brightspot.cloud/privacy-center/en-us/privacy-statement?s=00000195-202e-ddef-a3f7-213fc5d00000&p=00000195-202a-ddef-a3f7-213b3e7b0000 | B33: https://thenext.jnjmedtech.com/ | C33: =IFERROR(XLOOKUP(B33,'Deduped URLs'!A:A,'Deduped URLs'!B:B,""),"") | D33: Medical devices & technology | F33: 301 | G33: Moved Permanently | H33: Absolute | I33: //body/bsp-header/div[@class='Page-header-topNav-container']/nav/ul/li[1]/ul/li[@class='GlobalSiteNavigation-items-item'][3]/div/div/a | J33: Navigation | K33: HTML & Rendered HTML
A34: https://jnj-uat.lower.jnj.brightspot.cloud/privacy-center/en-us/privacy-statement?s=00000195-202e-ddef-a3f7-213fc5d00000&p=00000195-202a-ddef-a3f7-213b3e7b0000 | B34: https://thenext.jnjmedtech.com/ | C34: =IFERROR(XLOOKUP(B34,'Deduped URLs'!A:A,'Deduped URLs'!B:B,""),"") | D34: Medical devices & technology | F34: 301 | G34: Moved Permanently | H34: Absolute | I34: //body/bsp-header/div[@class='Page-header-topNav-container']/nav/ul/li[1]/div/ul/li[@class='GlobalSiteNavigation-items-item'][3]/div/div/a | J34: Navigation | K34: HTML & Rendered HTML
A35: https://jnj-uat.lower.jnj.brightspot.cloud/privacy-center/en-us/privacy-statement?s=00000195-202e-ddef-a3f7-213fc5d00000&p=00000195-202a-ddef-a3f7-213b3e7b0000 | B35: https://thenext.jnjmedtech.com/ | C35: =IFERROR(XLOOKUP(B35,'Deduped URLs'!A:A,'Deduped URLs'!B:B,""),"") | D35: Medical devices & technology | F35: 301 | G35: Moved Permanently | H35: Absolute | I35: //body/footer/div/div[@class='Page-footer-columns']/div/div/bsp-footer-nav/ul/li[@class='FooterNavigation-items-item'][1]/div/ul/li[@class='FooterNavigationItem-items-item'][3]/a | J35: Navigation | K35: HTML & Rendered HTML
A36: https://jnj-uat.lower.jnj.brightspot.cloud/innovativemedicine/belgium/fr | B36: https://thenext.jnjmedtech.com/ | C36: https://www.jnjmedtech.com/ | D36: Medical devices & technology | F36: 301 | G36: Moved Permanently | H36: Absolute | I36: //body/bsp-header/div[@class='Page-header-topNav-container']/nav/ul/li[1]/ul/li[@class='GlobalSiteNavigation-items-item'][3]/div/div/a | J36: Navigation | K36: HTML & Rendered HTML
A37: https://jnj-uat.lower.jnj.brightspot.cloud/innovativemedicine/belgium/fr | B37: https://thenext.jnjmedtech.com/ | C37: https://www.jnjmedtech.com/ | D37: Medical devices & technology | F37: 301 | G37: Moved Permanently | H37: Absolute | I37: //body/bsp-header/div[@class='Page-header-topNav-container']/nav/ul/li[1]/div/ul/li[@class='GlobalSiteNavigation-items-item'][3]/div/div/a | J37: Navigation | K37: HTML & Rendered HTML
A38: https://jnj-uat.lower.jnj.brightspot.cloud/innovativemedicine/belgium/nl | B38: https://thenext.jnjmedtech.com/ | C38: https://www.jnjmedtech.com/ | D38: Medical devices & technology | F38: 301 | G38: Moved Permanently | H38: Absolute | I38: //body/bsp-header/div[@class='Page-header-topNav-container']/nav/ul/li[1]/ul/li[@class='GlobalSiteNavigation-items-item'][3]/div/div/a | J38: Navigation | K38: HTML & Rendered HTML
A39: https://jnj-uat.lower.jnj.brightspot.cloud/innovativemedicine/belgium/nl | B39: https://thenext.jnjmedtech.com/ | C39: https://www.jnjmedtech.com/ | D39: Medical devices & technology | F39: 301 | G39: Moved Permanently | H39: Absolute | I39: //body/bsp-header/div[@class='Page-header-topNav-container']/nav/ul/li[1]/div/ul/li[@class='GlobalSiteNavigation-items-item'][3]/div/div/a | J39: Navigation | K39: HTML & Rendered HTML
A40: https://jnj-uat.lower.jnj.brightspot.cloud/innovativemedicine/sweden/ | B40: https://thenext.jnjmedtech.com/ | C40: https://www.jnjmedtech.com/ | D40: Medical devices & technology | F40: 301 | G40: Moved Permanently | H40: Absolute | I40: //body/bsp-header/div[@class='Page-header-topNav-container']/nav/ul/li[1]/ul/li[@class='GlobalSiteNavigation-items-item'][3]/div/div/a | J40: Navigation | K40: HTML & Rendered HTML
A41: https://jnj-uat.lower.jnj.brightspot.cloud/innovativemedicine/sweden/ | B41: https://thenext.jnjmedtech.com/ | C41: https://www.jnjmedtech.com/ | D41: Medical devices & technology | F41: 301 | G41: Moved Permanently | H41: Absolute | I41: //body/bsp-header/div[@class='Page-header-topNav-container']/nav/ul/li[1]/div/ul/li[@class='GlobalSiteNavigation-items-item'][3]/div/div/a | J41: Navigation | K41: HTML & Rendered HTML
A42: https://jnj-uat.lower.jnj.brightspot.cloud/innovativemedicine/canada/fr | B42: https://thenext.jnjmedtech.com/ | C42: https://www.jnjmedtech.com/ | D42: Medical devices & technology | F42: 301 | G42: Moved Permanently | H42: Absolute | I42: //body/bsp-header/div[@class='Page-header-topNav-container']/nav/ul/li[1]/ul/li[@class='GlobalSiteNavigation-items-item'][3]/div/div/a | J42: Navigation | K42: HTML & Rendered HTML
A43: https://jnj-uat.lower.jnj.brightspot.cloud/innovativemedicine/canada/fr | B43: https://thenext.jnjmedtech.com/ | C43: https://www.jnjmedtech.com/ | D43: Medical devices & technology | F43: 301 | G43: Moved Permanently | H43: Absolute | I43: //body/bsp-header/div[@class='Page-header-topNav-container']/nav/ul/li[1]/div/ul/li[@class='GlobalSiteNavigation-items-item'][3]/div/div/a | J43: Navigation | K43: HTML & Rendered HTML
A44: https://jnj-uat.lower.jnj.brightspot.cloud/innovativemedicine/us/ | B44: https://thenext.jnjmedtech.com/ | C44: =IFERROR(XLOOKUP(B44,'Deduped URLs'!A:A,'Deduped URLs'!B:B,""),"") | D44: Medical devices & technology | F44: 301 | G44: Moved Permanently | H44: Absolute | I44: //body/bsp-header/div[@class='Page-header-topNav-container']/nav/ul/li[1]/ul/li[@class='GlobalSiteNavigation-items-item'][3]/div/div/a | J44: Navigation | K44: HTML & Rendered HTML
A45: https://jnj-uat.lower.jnj.brightspot.cloud/innovativemedicine/us/ | B45: https://thenext.jnjmedtech.com/ | C45: =IFERROR(XLOOKUP(B45,'Deduped URLs'!A:A,'Deduped URLs'!B:B,""),"") | D45: Medical devices & technology | F45: 301 | G45: Moved Permanently | H45: Absolute | I45: //body/bsp-header/div[@class='Page-header-topNav-container']/nav/ul/li[1]/div/ul/li[@class='GlobalSiteNavigation-items-item'][3]/div/div/a | J45: Navigation | K45: HTML & Rendered HTML
A46: https://jnj-uat.lower.jnj.brightspot.cloud/innovativemedicine/us/ | B46: https://thenext.jnjmedtech.com/ | C46: =IFERROR(XLOOKUP(B46,'Deduped URLs'!A:A,'Deduped URLs'!B:B,""),"") | D46: Products | F46: 301 | G46: Moved Permanently | H46: Absolute | I46: //body/footer/div/div[@class='Page-footer-columns']/div/div/bsp-footer-nav/ul/li[@class='FooterNavigation-items-item'][3]/div/ul/li[@class='FooterNavigationItem-items-item'][1]/a | J46: Navigation | K46: HTML & Rendered HTML
A47: https://jnj-uat.lower.jnj.brightspot.cloud/innovativemedicine/peru/ | B47: https://thenext.jnjmedtech.com/ | C47: https://www.jnjmedtech.com/ | D47: Medical devices & technology | F47: 301 | G47: Moved Permanently | H47: Absolute | I47: //body/bsp-header/div[@class='Page-header-topNav-container']/nav/ul/li[1]/ul/li[@class='GlobalSiteNavigation-items-item'][3]/div/div/a | J47: Navigation | K47: HTML & Rendered HTML
A48: https://jnj-uat.lower.jnj.brightspot.cloud/innovativemedicine/peru/ | B48: https://thenext.jnjmedtech.com/ | C48: https://www.jnjmedtech.com/ | D48: Medical devices & technology | F48: 301 | G48: Moved Permanently | H48: Absolute | I48: //body/bsp-header/div[@class='Page-header-topNav-container']/nav/ul/li[1]/div/ul/li[@class='GlobalSiteNavigation-items-item'][3]/div/div/a | J48: Navigation | K48: HTML & Rendered HTML
A49: https://jnj-uat.lower.jnj.brightspot.cloud/innovativemedicine/chile/ | B49: https://thenext.jnjmedtech.com/ | C49: https://www.jnjmedtech.com/ | D49: Medical devices & technology | F49: 301 | G49: Moved Permanently | H49: Absolute | I49: //body/bsp-header/div[@class='Page-header-topNav-container']/nav/ul/li[1]/ul/li[@class='GlobalSiteNavigation-items-item'][3]/div/div/a | J49: Navigation | K49: HTML & Rendered HTML
A50: https://jnj-uat.lower.jnj.brightspot.cloud/innovativemedicine/chile/ | B50: https://thenext.jnjmedtech.com/ | C50: https://www.jnjmedtech.com/ | D50: Medical devices & technology | F50: 301 | G50: Moved Permanently | H50: Absolute | I50: //body/bsp-header/div[@class='Page-header-topNav-container']/nav/ul/li[1]/div/ul/li[@class='GlobalSiteNavigation-items-item'][3]/div/div/a | J50: Navigation | K50: HTML & Rendered HTML
A51: https://jnj-uat.lower.jnj.brightspot.cloud/innovativemedicine/cenca/ | B51: https://thenext.jnjmedtech.com/ | C51: https://www.jnjmedtech.com/ | D51: Medical devices & technology | F51: 301 | G51: Moved Permanently | H51: Absolute | I51: //body/bsp-header/div[@class='Page-header-topNav-container']/nav/ul/li[1]/ul/li[@class='GlobalSiteNavigation-items-item'][3]/div/div/a | J51: Navigation | K51: HTML & Rendered HTML
A52: https://jnj-uat.lower.jnj.brightspot.cloud/innovativemedicine/cenca/ | B52: https://thenext.jnjmedtech.com/ | C52: https://www.jnjmedtech.com/ | D52: Medical devices & technology | F52: 301 | G52: Moved Permanently | H52: Absolute | I52: //body/bsp-header/div[@class='Page-header-topNav-container']/nav/ul/li[1]/div/ul/li[@class='GlobalSiteNavigation-items-item'][3]/div/div/a | J52: Navigation | K52: HTML & Rendered HTML
A53: https://jnj-uat.lower.jnj.brightspot.cloud/media-center/press-releases/johnson-johnson-completes-catheter-portfolio-with-launch-of-cereglide-42-cereglide-57-and-innerglide-7 | B53: https://thenext.jnjmedtech.com/ | C53: =IFERROR(XLOOKUP(B53,'Deduped URLs'!A:A,'Deduped URLs'!B:B,""),"") | D53: thenext.jnjmedtech.com | F53: 301 | G53: Moved Permanently | H53: Absolute | I53: //body/div[@id='main']/div[@class='Page-oneColumn']/main/div/div[1]/p[9]/span[@class='LinkEnhancement'][1]/a | J53: Content | K53: HTML & Rendered HTML
A54: https://jnj-uat.lower.jnj.brightspot.cloud/privacy-center/en-us/privacy-statement | B54: https://thenext.jnjmedtech.com/ | C54: =IFERROR(XLOOKUP(B54,'Deduped URLs'!A:A,'Deduped URLs'!B:B,""),"") | D54: Medical devices & technology | F54: 301 | G54: Moved Permanently | H54: Absolute | I54: //body/bsp-header/div[@class='Page-header-topNav-container']/nav/ul/li[1]/ul/li[@class='GlobalSiteNavigation-items-item'][3]/div/div/a | J54: Navigation | K54: HTML & Rendered HTML
A55: https://jnj-uat.lower.jnj.brightspot.cloud/privacy-center/en-us/privacy-statement | B55: https://thenext.jnjmedtech.com/ | C55: =IFERROR(XLOOKUP(B55,'Deduped URLs'!A:A,'Deduped URLs'!B:B,""),"") | D55: Medical devices & technology | F55: 301 | G55: Moved Permanently | H55: Absolute | I55: //body/bsp-header/div[@class='Page-header-topNav-container']/nav/ul/li[1]/div/ul/li[@class='GlobalSiteNavigation-items-item'][3]/div/div/a | J55: Navigation | K55: HTML & Rendered HTML
A56: https://jnj-uat.lower.jnj.brightspot.cloud/privacy-center/en-us/privacy-statement | B56: https://thenext.jnjmedtech.com/ | C56: =IFERROR(XLOOKUP(B56,'Deduped URLs'!A:A,'Deduped URLs'!B:B,""),"") | D56: Medical devices & technology | F56: 301 | G56: Moved Permanently | H56: Absolute | I56: //body/footer/div/div[@class='Page-footer-columns']/div/div/bsp-footer-nav/ul/li[@class='FooterNavigation-items-item'][1]/div/ul/li[@class='FooterNavigationItem-items-item'][3]/a | J56: Navigation | K56: HTML & Rendered HTML
A57: https://jnj-uat.lower.jnj.brightspot.cloud/innovativemedicine/ireland/about-us/our-presence-in-ireland | B57: https://thenext.jnjmedtech.com/ | C57: https://www.jnjmedtech.com/ | D57: Medical devices & technology | F57: 301 | G57: Moved Permanently | H57: Absolute | I57: //body/bsp-header/div[@class='Page-header-topNav-container']/nav/ul/li[1]/ul/li[@class='GlobalSiteNavigation-items-item'][3]/div/div/a | J57: Navigation | K57: HTML & Rendered HTML
A58: https://jnj-uat.lower.jnj.brightspot.cloud/innovativemedicine/ireland/about-us/our-presence-in-ireland | B58: https://thenext.jnjmedtech.com/ | C58: https://www.jnjmedtech.com/ | D58: Medical devices & technology | F58: 301 | G58: Moved Permanently | H58: Absolute | I58: //body/bsp-header/div[@class='Page-header-topNav-container']/nav/ul/li[1]/div/ul/li[@class='GlobalSiteNavigation-items-item'][3]/div/div/a | J58: Navigation | K58: HTML & Rendered HTML
A59: https://jnj-uat.lower.jnj.brightspot.cloud/media-center/press-releases/johnson-johnson-reaches-50-million-children-through-sight-for-kids-program | B59: https://thenext.jnjmedtech.com/ | C59: {=IFERROR(XLOOKUP(B59,'Deduped URLs'!A:A,'Deduped URLs'!B:B,""),"")} | D59: https://thenext.jnjmedtech.com | F59: 301 | G59: Moved Permanently | H59: Absolute | I59: //body/div[@id='main']/div[@class='Page-oneColumn']/main/div/div[1]/p[9]/span[@class='LinkEnhancement']/a | J59: Content | K59: HTML & Rendered HTML
A60: https://jnj-uat.lower.jnj.brightspot.cloud/CH/fr/community-impact | B60: https://thenext.jnjmedtech.com/ | C60: https://www.jnjmedtech.com/ | D60: J&J MedTech | F60: 301 | G60: Moved Permanently | H60: Absolute | I60: //body/bsp-header/div[@class='Page-header-topNav-container']/nav/ul/li[1]/ul/li[@class='GlobalSiteNavigation-items-item'][3]/div/div/a | J60: Navigation | K60: HTML & Rendered HTML
A61: https://jnj-uat.lower.jnj.brightspot.cloud/CH/fr/community-impact | B61: https://thenext.jnjmedtech.com/ | C61: https://www.jnjmedtech.com/ | D61: J&J MedTech | F61: 301 | G61: Moved Permanently | H61: Absolute | I61: //body/bsp-header/div[@class='Page-header-topNav-container']/nav/ul/li[1]/div/ul/li[@class='GlobalSiteNavigation-items-item'][3]/div/div/a | J61: Navigation | K61: HTML & Rendered HTML
A62: https://jnj-uat.lower.jnj.brightspot.cloud/CH/fr/centre-media/ | B62: https://thenext.jnjmedtech.com/ | C62: https://www.jnjmedtech.com/ | D62: J&J MedTech | F62: 301 | G62: Moved Permanently | H62: Absolute | I62: //body/bsp-header/div[@class='Page-header-topNav-container']/nav/ul/li[1]/ul/li[@class='GlobalSiteNavigation-items-item'][3]/div/div/a | J62: Navigation | K62: HTML & Rendered HTML
A63: https://jnj-uat.lower.jnj.brightspot.cloud/CH/fr/centre-media/ | B63: https://thenext.jnjmedtech.com/ | C63: https://www.jnjmedtech.com/ | D63: J&J MedTech | F63: 301 | G63: Moved Permanently | H63: Absolute | I63: //body/bsp-header/div[@class='Page-header-topNav-container']/nav/ul/li[1]/div/ul/li[@class='GlobalSiteNavigation-items-item'][3]/div/div/a | J63: Navigation | K63: HTML & Rendered HTML
A64: https://jnj-uat.lower.jnj.brightspot.cloud/CH/partnerships | B64: https://thenext.jnjmedtech.com/ | C64: https://www.jnjmedtech.com/ | D64: J&J MedTech | F64: 301 | G64: Moved Permanently | H64: Absolute | I64: //body/bsp-header/div[@class='Page-header-topNav-container']/nav/ul/li[1]/ul/li[@class='GlobalSiteNavigation-items-item'][3]/div/div/a | J64: Navigation | K64: HTML & Rendered HTML
A65: https://jnj-uat.lower.jnj.brightspot.cloud/CH/partnerships | B65: https://thenext.jnjmedtech.com/ | C65: https://www.jnjmedtech.com/ | D65: J&J MedTech | F65: 301 | G65: Moved Permanently | H65: Absolute | I65: //body/bsp-header/div[@class='Page-header-topNav-container']/nav/ul/li[1]/div/ul/li[@class='GlobalSiteNavigation-items-item'][3]/div/div/a | J65: Navigation | K65: HTML & Rendered HTML
A66: https://jnj-uat.lower.jnj.brightspot.cloud/CH/fr/avantages-sociaux | B66: https://thenext.jnjmedtech.com/ | C66: https://www.jnjmedtech.com/ | D66: J&J MedTech | F66: 301 | G66: Moved Permanently | H66: Absolute | I66: //body/bsp-header/div[@class='Page-header-topNav-container']/nav/ul/li[1]/ul/li[@class='GlobalSiteNavigation-items-item'][3]/div/div/a | J66: Navigation | K66: HTML & Rendered HTML
A67: https://jnj-uat.lower.jnj.brightspot.cloud/CH/fr/avantages-sociaux | B67: https://thenext.jnjmedtech.com/ | C67: https://www.jnjmedtech.com/ | D67: J&J MedTech | F67: 301 | G67: Moved Permanently | H67: Absolute | I67: //body/bsp-header/div[@class='Page-header-topNav-container']/nav/ul/li[1]/div/ul/li[@class='GlobalSiteNavigation-items-item'][3]/div/div/a | J67: Navigation | K67: HTML & Rendered HTML
A68: https://jnj-uat.lower.jnj.brightspot.cloud/CH/careers | B68: https://thenext.jnjmedtech.com/ | C68: https://www.jnjmedtech.com/ | D68: J&J MedTech | F68: 301 | G68: Moved Permanently | H68: Absolute | I68: //body/bsp-header/div[@class='Page-header-topNav-container']/nav/ul/li[1]/ul/li[@class='GlobalSiteNavigation-items-item'][3]/div/div/a | J68: Navigation | K68: HTML & Rendered HTML
A69: https://jnj-uat.lower.jnj.brightspot.cloud/CH/careers | B69: https://thenext.jnjmedtech.com/ | C69: https://www.jnjmedtech.com/ | D69: J&J MedTech | F69: 301 | G69: Moved Permanently | H69: Absolute | I69: //body/bsp-header/div[@class='Page-header-topNav-container']/nav/ul/li[1]/div/ul/li[@class='GlobalSiteNavigation-items-item'][3]/div/div/a | J69: Navigation | K69: HTML & Rendered HTML
A70: https://jnj-uat.lower.jnj.brightspot.cloud/CH/de/medien-center/ | B70: https://thenext.jnjmedtech.com/ | C70: https://www.jnjmedtech.com/ | D70: J&J MedTech | F70: 301 | G70: Moved Permanently | H70: Absolute | I70: //body/bsp-header/div[@class='Page-header-topNav-container']/nav/ul/li[1]/ul/li[@class='GlobalSiteNavigation-items-item'][3]/div/div/a | J70: Navigation | K70: HTML & Rendered HTML
A71: https://jnj-uat.lower.jnj.brightspot.cloud/CH/de/medien-center/ | B71: https://thenext.jnjmedtech.com/ | C71: https://www.jnjmedtech.com/ | D71: J&J MedTech | F71: 301 | G71: Moved Permanently | H71: Absolute | I71: //body/bsp-header/div[@class='Page-header-topNav-container']/nav/ul/li[1]/div/ul/li[@class='GlobalSiteNavigation-items-item'][3]/div/div/a | J71: Navigation | K71: HTML & Rendered HTML
... A233: https://jnj-uat.lower.jnj.brightspot.cloud/innovativemedicine/australia/ | B233: https://thenext.jnjmedtech.com/ | C233: https://www.jnjmedtech.com/ | D233: Medical devices & technology | F233: 301 | G233: Moved Permanently | H233: Absolute | I233: //body/bsp-header/div[@class='Page-header-topNav-container']/nav/ul/li[1]/div/ul/li[@class='GlobalSiteNavigation-items-item'][3]/div/div/a | J233: Navigation | K233: HTML & Rendered HTML
A234: https://jnj-uat.lower.jnj.brightspot.cloud/privacy-center/en-us/washington-consumer-health-data-privacy-notice | B234: https://thenext.jnjmedtech.com/ | C234: =IFERROR(XLOOKUP(B234,'Deduped URLs'!A:A,'Deduped URLs'!B:B,""),"") | D234: Medical devices & technology | F234: 301 | G234: Moved Permanently | H234: Absolute | I234: //body/bsp-header/div[@class='Page-header-topNav-container']/nav/ul/li[1]/ul/li[@class='GlobalSiteNavigation-items-item'][3]/div/div/a | J234: Navigation | K234: HTML & Rendered HTML
A235: https://jnj-uat.lower.jnj.brightspot.cloud/privacy-center/en-us/washington-consumer-health-data-privacy-notice | B235: https://thenext.jnjmedtech.com/ | C235: =IFERROR(XLOOKUP(B235,'Deduped URLs'!A:A,'Deduped URLs'!B:B,""),"") | D235: Medical devices & technology | F235: 301 | G235: Moved Permanently | H235: Absolute | I235: //body/bsp-header/div[@class='Page-header-topNav-container']/nav/ul/li[1]/div/ul/li[@class='GlobalSiteNavigation-items-item'][3]/div/div/a | J235: Navigation | K235: HTML & Rendered HTML
A236: https://jnj-uat.lower.jnj.brightspot.cloud/privacy-center/en-us/washington-consumer-health-data-privacy-notice | B236: https://thenext.jnjmedtech.com/ | C236: =IFERROR(XLOOKUP(B236,'Deduped URLs'!A:A,'Deduped URLs'!B:B,""),"") | D236: Medical devices & technology | F236: 301 | G236: Moved Permanently | H236: Absolute | I236: //body/footer/div/div[@class='Page-footer-columns']/div/div/bsp-footer-nav/ul/li[@class='FooterNavigation-items-item'][1]/div/ul/li[@class='FooterNavigationItem-items-item'][3]/a | J236: Navigation | K236: HTML & Rendered HTML
A237: https://jnj-uat.lower.jnj.brightspot.cloud/privacy-center/es-us | B237: https://thenext.jnjmedtech.com/ | C237: =IFERROR(XLOOKUP(B237,'Deduped URLs'!A:A,'Deduped URLs'!B:B,""),"") | D237: Medical devices & technology | F237: 301 | G237: Moved Permanently | H237: Absolute | I237: //body/bsp-header/div[@class='Page-header-topNav-container']/nav/ul/li[1]/ul/li[@class='GlobalSiteNavigation-items-item'][3]/div/div/a | J237: Navigation | K237: HTML & Rendered HTML
A238: https://jnj-uat.lower.jnj.brightspot.cloud/privacy-center/es-us | B238: https://thenext.jnjmedtech.com/ | C238: =IFERROR(XLOOKUP(B238,'Deduped URLs'!A:A,'Deduped URLs'!B:B,""),"") | D238: Medical devices & technology | F238: 301 | G238: Moved Permanently | H238: Absolute | I238: //body/bsp-header/div[@class='Page-header-topNav-container']/nav/ul/li[1]/div/ul/li[@class='GlobalSiteNavigation-items-item'][3]/div/div/a | J238: Navigation | K238: HTML & Rendered HTML
A239: https://jnj-uat.lower.jnj.brightspot.cloud/privacy-center/es-us | B239: https://thenext.jnjmedtech.com/ | C239: =IFERROR(XLOOKUP(B239,'Deduped URLs'!A:A,'Deduped URLs'!B:B,""),"") | D239: Dispositivos médicos y tecnología | F239: 301 | G239: Moved Permanently | H239: Absolute | I239: //body/footer/div/div[@class='Page-footer-columns']/div/div/bsp-footer-nav/ul/li[@class='FooterNavigation-items-item'][1]/div/ul/li[@class='FooterNavigationItem-items-item'][3]/a | J239: Navigation | K239: HTML & Rendered HTML
A240: https://jnj-uat.lower.jnj.brightspot.cloud/privacy-center/en-us/affiliates | B240: https://thenext.jnjmedtech.com/ | C240: =IFERROR(XLOOKUP(B240,'Deduped URLs'!A:A,'Deduped URLs'!B:B,""),"") | D240: Medical devices & technology | F240: 301 | G240: Moved Permanently | H240: Absolute | I240: //body/bsp-header/div[@class='Page-header-topNav-container']/nav/ul/li[1]/ul/li[@class='GlobalSiteNavigation-items-item'][3]/div/div/a | J240: Navigation | K240: HTML & Rendered HTML
A241: https://jnj-uat.lower.jnj.brightspot.cloud/privacy-center/en-us/affiliates | B241: https://thenext.jnjmedtech.com/ | C241: =IFERROR(XLOOKUP(B241,'Deduped URLs'!A:A,'Deduped URLs'!B:B,""),"") | D241: Medical devices & technology | F241: 301 | G241: Moved Permanently | H241: Absolute | I241: //body/bsp-header/div[@class='Page-header-topNav-container']/nav/ul/li[1]/div/ul/li[@class='GlobalSiteNavigation-items-item'][3]/div/div/a | J241: Navigation | K241: HTML & Rendered HTML
A242: https://jnj-uat.lower.jnj.brightspot.cloud/privacy-center/en-us/affiliates | B242: https://thenext.jnjmedtech.com/ | C242: =IFERROR(XLOOKUP(B242,'Deduped URLs'!A:A,'Deduped URLs'!B:B,""),"") | D242: Medical devices & technology | F242: 301 | G242: Moved Permanently | H242: Absolute | I242: //body/footer/div/div[@class='Page-footer-columns']/div/div/bsp-footer-nav/ul/li[@class='FooterNavigation-items-item'][1]/div/ul/li[@class='FooterNavigationItem-items-item'][3]/a | J242: Navigation | K242: HTML & Rendered HTML
A243: https://jnj-uat.lower.jnj.brightspot.cloud/privacy-center/en-ca | B243: https://thenext.jnjmedtech.com/ | C243: https://www.jnjmedtech.com/ | D243: Medical devices & technology | F243: 301 | G243: Moved Permanently | H243: Absolute | I243: //body/bsp-header/div[@class='Page-header-topNav-container']/nav/ul/li[1]/ul/li[@class='GlobalSiteNavigation-items-item'][3]/div/div/a | J243: Navigation | K243: HTML & Rendered HTML
A244: https://jnj-uat.lower.jnj.brightspot.cloud/privacy-center/en-ca | B244: https://thenext.jnjmedtech.com/ | C244: https://www.jnjmedtech.com/ | D244: Medical devices & technology | F244: 301 | G244: Moved Permanently | H244: Absolute | I244: //body/bsp-header/div[@class='Page-header-topNav-container']/nav/ul/li[1]/div/ul/li[@class='GlobalSiteNavigation-items-item'][3]/div/div/a | J244: Navigation | K244: HTML & Rendered HTML
A245: https://jnj-uat.lower.jnj.brightspot.cloud/privacy-center/en-ca | B245: https://thenext.jnjmedtech.com/ | C245: https://www.jnjmedtech.com/ | D245: Medical devices & technology | F245: 301 | G245: Moved Permanently | H245: Absolute | I245: //body/footer/div/div[@class='Page-footer-columns']/div/div/bsp-footer-nav/ul/li[@class='FooterNavigation-items-item'][1]/div/ul/li[@class='FooterNavigationItem-items-item'][3]/a | J245: Navigation | K245: HTML & Rendered HTML
A246: https://jnj-uat.lower.jnj.brightspot.cloud/privacy-center/en-us/privacy-statement?s=00000195-2026-debe-abb7-a336ba8c0000&p=00000195-202a-ddef-a3f7-213b3e7b0000 | B246: https://thenext.jnjmedtech.com/ | C246: =IFERROR(XLOOKUP(B246,'Deduped URLs'!A:A,'Deduped URLs'!B:B,""),"") | D246: Medical devices & technology | F246: 301 | G246: Moved Permanently | H246: Absolute | I246: //body/bsp-header/div[@class='Page-header-topNav-container']/nav/ul/li[1]/ul/li[@class='GlobalSiteNavigation-items-item'][3]/div/div/a | J246: Navigation | K246: HTML & Rendered HTML
A247: https://jnj-uat.lower.jnj.brightspot.cloud/privacy-center/en-us/privacy-statement?s=00000195-2026-debe-abb7-a336ba8c0000&p=00000195-202a-ddef-a3f7-213b3e7b0000 | B247: https://thenext.jnjmedtech.com/ | C247: =IFERROR(XLOOKUP(B247,'Deduped URLs'!A:A,'Deduped URLs'!B:B,""),"") | D247: Medical devices & technology | F247: 301 | G247: Moved Permanently | H247: Absolute | I247: //body/bsp-header/div[@class='Page-header-topNav-container']/nav/ul/li[1]/div/ul/li[@class='GlobalSiteNavigation-items-item'][3]/div/div/a | J247: Navigation | K247: HTML & Rendered HTML
A248: https://jnj-uat.lower.jnj.brightspot.cloud/privacy-center/en-us/privacy-statement?s=00000195-2026-debe-abb7-a336ba8c0000&p=00000195-202a-ddef-a3f7-213b3e7b0000 | B248: https://thenext.jnjmedtech.com/ | C248: =IFERROR(XLOOKUP(B248,'Deduped URLs'!A:A,'Deduped URLs'!B:B,""),"") | D248: Medical devices & technology | F248: 301 | G248: Moved Permanently | H248: Absolute | I248: //body/footer/div/div[@class='Page-footer-columns']/div/div/bsp-footer-nav/ul/li[@class='FooterNavigation-items-item'][1]/div/ul/li[@class='FooterNavigationItem-items-item'][3]/a | J248: Navigation | K248: HTML & Rendered HTML
A249: https://jnj-uat.lower.jnj.brightspot.cloud/privacy-center/en-us/glossary | B249: https://thenext.jnjmedtech.com/ | C249: =IFERROR(XLOOKUP(B249,'Deduped URLs'!A:A,'Deduped URLs'!B:B,""),"") | D249: Medical devices & technology | F249: 301 | G249: Moved Permanently | H249: Absolute | I249: //body/bsp-header/div[@class='Page-header-topNav-container']/nav/ul/li[1]/ul/li[@class='GlobalSiteNavigation-items-item'][3]/div/div/a | J249: Navigation | K249: HTML & Rendered HTML
A250: https://jnj-uat.lower.jnj.brightspot.cloud/privacy-center/en-us/glossary | B250: https://thenext.jnjmedtech.com/ | C250: =IFERROR(XLOOKUP(B250,'Deduped URLs'!A:A,'Deduped URLs'!B:B,""),"") | D250: Medical devices & technology | F250: 301 | G250: Moved Permanently | H250: Absolute | I250: //body/bsp-header/div[@class='Page-header-topNav-container']/nav/ul/li[1]/div/ul/li[@class='GlobalSiteNavigation-items-item'][3]/div/div/a | J250: Navigation | K250: HTML & Rendered HTML
A251: https://jnj-uat.lower.jnj.brightspot.cloud/privacy-center/en-us/glossary | B251: https://thenext.jnjmedtech.com/ | C251: =IFERROR(XLOOKUP(B251,'Deduped URLs'!A:A,'Deduped URLs'!B:B,""),"") | D251: Medical devices & technology | F251: 301 | G251: Moved Permanently | H251: Absolute | I251: //body/footer/div/div[@class='Page-footer-columns']/div/div/bsp-footer-nav/ul/li[@class='FooterNavigation-items-item'][1]/div/ul/li[@class='FooterNavigationItem-items-item'][3]/a | J251: Navigation | K251: HTML & Rendered HTML
A252: https://jnj-uat.lower.jnj.brightspot.cloud/privacy-center/es-us/privacy-statement | B252: https://thenext.jnjmedtech.com/ | C252: =IFERROR(XLOOKUP(B252,'Deduped URLs'!A:A,'Deduped URLs'!B:B,""),"") | D252: Medical devices & technology | F252: 301 | G252: Moved Permanently | H252: Absolute | I252: //body/bsp-header/div[@class='Page-header-topNav-container']/nav/ul/li[1]/ul/li[@class='GlobalSiteNavigation-items-item'][3]/div/div/a | J252: Navigation | K252: HTML & Rendered HTML
A253: https://jnj-uat.lower.jnj.brightspot.cloud/privacy-center/es-us/privacy-statement | B253: https://thenext.jnjmedtech.com/ | C253: =IFERROR(XLOOKUP(B253,'Deduped URLs'!A:A,'Deduped URLs'!B:B,""),"") | D253: Medical devices & technology | F253: 301 | G253: Moved Permanently | H253: Absolute | I253: //body/bsp-header/div[@class='Page-header-topNav-container']/nav/ul/li[1]/div/ul/li[@class='GlobalSiteNavigation-items-item'][3]/div/div/a | J253: Navigation | K253: HTML & Rendered HTML
A254: https://jnj-uat.lower.jnj.brightspot.cloud/privacy-center/es-us/privacy-statement | B254: https://thenext.jnjmedtech.com/ | C254: =IFERROR(XLOOKUP(B254,'Deduped URLs'!A:A,'Deduped URLs'!B:B,""),"") | D254: Dispositivos médicos y tecnología | F254: 301 | G254: Moved Permanently | H254: Absolute | I254: //body/footer/div/div[@class='Page-footer-columns']/div/div/bsp-footer-nav/ul/li[@class='FooterNavigation-items-item'][1]/div/ul/li[@class='FooterNavigationItem-items-item'][3]/a | J254: Navigation | K254: HTML & Rendered HTML
A255: https://jnj-uat.lower.jnj.brightspot.cloud/privacy-center/fr-ca | B255: https://thenext.jnjmedtech.com/ | C255: https://www.jnjmedtech.com/ | D255: Medical devices & technology | F255: 301 | G255: Moved Permanently | H255: Absolute | I255: //body/bsp-header/div[@class='Page-header-topNav-container']/nav/ul/li[1]/ul/li[@class='GlobalSiteNavigation-items-item'][3]/div/div/a | J255: Navigation | K255: HTML & Rendered HTML
A256: https://jnj-uat.lower.jnj.brightspot.cloud/privacy-center/fr-ca | B256: https://thenext.jnjmedtech.com/ | C256: https://www.jnjmedtech.com/ | D256: Medical devices & technology | F256: 301 | G256: Moved Permanently | H256: Absolute | I256: //body/bsp-header/div[@class='Page-header-topNav-container']/nav/ul/li[1]/div/ul/li[@class='GlobalSiteNavigation-items-item'][3]/div/div/a | J256: Navigation | K256: HTML & Rendered HTML
A257: https://jnj-uat.lower.jnj.brightspot.cloud/privacy-center/fr-ca | B257: https://thenext.jnjmedtech.com/ | C257: https://www.jnjmedtech.com/ | D257: Matériels médicaux et technologie | F257: 301 | G257: Moved Permanently | H257: Absolute | I257: //body/footer/div/div[@class='Page-footer-columns']/div/div/bsp-footer-nav/ul/li[@class='FooterNavigation-items-item'][1]/div/ul/li[@class='FooterNavigationItem-items-item'][3]/a | J257: Navigation | K257: HTML & Rendered HTML
A258: https://jnj-uat.lower.jnj.brightspot.cloud/privacy-center/en-us/us-states-supplemental-privacy-statement | B258: https://thenext.jnjmedtech.com/ | C258: =IFERROR(XLOOKUP(B258,'Deduped URLs'!A:A,'Deduped URLs'!B:B,""),"") | D258: Medical devices & technology | F258: 301 | G258: Moved Permanently | H258: Absolute | I258: //body/bsp-header/div[@class='Page-header-topNav-container']/nav/ul/li[1]/ul/li[@class='GlobalSiteNavigation-items-item'][3]/div/div/a | J258: Navigation | K258: HTML & Rendered HTML
A259: https://jnj-uat.lower.jnj.brightspot.cloud/privacy-center/en-us/us-states-supplemental-privacy-statement | B259: https://thenext.jnjmedtech.com/ | C259: =IFERROR(XLOOKUP(B259,'Deduped URLs'!A:A,'Deduped URLs'!B:B,""),"") | D259: Medical devices & technology | F259: 301 | G259: Moved Permanently | H259: Absolute | I259: //body/bsp-header/div[@class='Page-header-topNav-container']/nav/ul/li[1]/div/ul/li[@class='GlobalSiteNavigation-items-item'][3]/div/div/a | J259: Navigation | K259: HTML & Rendered HTML
A260: https://jnj-uat.lower.jnj.brightspot.cloud/privacy-center/en-us/us-states-supplemental-privacy-statement | B260: https://thenext.jnjmedtech.com/ | C260: =IFERROR(XLOOKUP(B260,'Deduped URLs'!A:A,'Deduped URLs'!B:B,""),"") | D260: Medical devices & technology | F260: 301 | G260: Moved Permanently | H260: Absolute | I260: //body/footer/div/div[@class='Page-footer-columns']/div/div/bsp-footer-nav/ul/li[@class='FooterNavigation-items-item'][1]/div/ul/li[@class='FooterNavigationItem-items-item'][3]/a | J260: Navigation | K260: HTML & Rendered HTML
A261: https://jnj-uat.lower.jnj.brightspot.cloud/privacy-center/en-us | B261: https://thenext.jnjmedtech.com/ | C261: =IFERROR(XLOOKUP(B261,'Deduped URLs'!A:A,'Deduped URLs'!B:B,""),"") | D261: Medical devices & technology | F261: 301 | G261: Moved Permanently | H261: Absolute | I261: //body/bsp-header/div[@class='Page-header-topNav-container']/nav/ul/li[1]/ul/li[@class='GlobalSiteNavigation-items-item'][3]/div/div/a | J261: Navigation | K261: HTML & Rendered HTML
...
